pynation/__init__.py
pynation/__main__.py
pynation/cli.py
pynation/data.py
pynation/utils.py
pynation-0.4.0.dist-info/entry_points.txt
pynation-0.4.0.dist-info/LICENSE
pynation-0.4.0.dist-info/WHEEL
pynation-0.4.0.dist-info/METADATA
pynation-0.4.0.dist-info/RECORD
