Metadata-Version: 2.1
Name: pynation
Version: 0.4.0
Summary: Find information about different countries.
Home-page: https://github.com/mrbazzan/pynation/
Author: Abdulwasiu Apalowo
Author-email: bazzanapalowo@gmail.com
Requires-Python: >=3.7
Classifier: License :: OSI Approved :: MIT License
Classifier: Operating System :: OS Independent
Classifier: Programming Language :: Python :: 3.7
Classifier: Topic :: Software Development :: Libraries
Requires-Dist: click==8.0.1
Requires-Dist: pytest==6.2.4 ; extra == "dev"
Project-URL: Documentation, https://github.com/mrbazzan/pynation/blob/main/README.md
Project-URL: Issues, https://github.com/mrbazzan/pynation/issues
Provides-Extra: dev
